nonebot_plugin_boom/__init__.py
nonebot_plugin_boom-0.1.2.dist-info/LICENSE
nonebot_plugin_boom-0.1.2.dist-info/METADATA
nonebot_plugin_boom-0.1.2.dist-info/WHEEL
nonebot_plugin_boom-0.1.2.dist-info/RECORD
