Metadata-Version: 2.1
Name: nonebot-plugin-boom
Version: 0.1.2
Summary: 【危险插件】炸炸你的NB
Author: Yeying-Xingchen
Author-email: yeyingxingchen@yeah.net
Requires-Python: >=3.9,<4.0
Classifier: Programming Language :: Python :: 3
Classifier: Programming Language :: Python :: 3.9
Classifier: Programming Language :: Python :: 3.10
Classifier: Programming Language :: Python :: 3.11
Classifier: Programming Language :: Python :: 3.12
Requires-Dist: nonebot2 (>=2.2.0,<3.0.0)
